{
  "seen": {
    "d7059996c3e7c114": {
      "title": "Mixer Mill Wins Selectscience Award",
      "first_seen": "2026-04-27"
    },
    "2b63e30d0da5ca39": {
      "title": "Verder Announces Acquisition of Sauermann",
      "first_seen": "2026-04-27"
    },
    "34c7dffe0c77620a": {
      "title": "Recap Verder Liquids@Achema 2024",
      "first_seen": "2026-04-27"
    },
    "5988330b3420938b": {
      "title": "A Tree for Every Verder Group Employee",
      "first_seen": "2026-04-27"
    },
    "c7370d3e53150a93": {
      "title": "Verder Liquids Team participated in 38th Baloise Antwerp 10 Miles",
      "first_seen": "2026-04-27"
    },
    "70449bd2d556aab5": {
      "title": "MICROTRAC Innovation Wins Readers' Award",
      "first_seen": "2026-04-27"
    },
    "a34ec26e5881feb0": {
      "title": "Verder Liquids Sales Meeting 2024: \"Always Further\" in Lisbon",
      "first_seen": "2026-04-27"
    },
    "3155bf6babfc7d91": {
      "title": "RETSCH honors pioneering research projects",
      "first_seen": "2026-04-27"
    },
    "eaa3fb56062cc34f": {
      "title": "Microtrac and Mark & Wedell partner up",
      "first_seen": "2026-04-27"
    },
    "3cafd7b67e7749b5": {
      "title": "RETSCH Scientific Challenge: Promote Your Project!",
      "first_seen": "2026-04-27"
    }
  },
  "last_run": "2026-04-27"
}